Metadata-Version: 1.0
Name: check-palindrome-aast
Version: 0.0.1
Summary: This is a palindrome checking function.
Home-page: https://asin1203.github.io
Author: Aastha Singh
Author-email: UNKNOWN
License: MIT
Keywords: palindrome,python palindrome,palindrome evaluator
Platform: UNKNOWN
